quiz_bots/app.py
quiz_bots/bots_helpers.py
quiz_bots/quiz.py
quiz_bots/quiz_helpers.py
quiz_bots/redis_utils.py
quiz_bots/settings.py
quiz_bots/tg_bot.py
quiz_bots/vk_bot.py
quiz_bots-0.2.2.dist-info/entry_points.txt
quiz_bots-0.2.2.dist-info/LICENSE
quiz_bots-0.2.2.dist-info/WHEEL
quiz_bots-0.2.2.dist-info/METADATA
quiz_bots-0.2.2.dist-info/RECORD
